ecpay_invoice/__init__.py
ecpay_invoice/ecpay_main.py
ecpay_invoice/ecpay_setting.py
ecpay_invoice-1.0.7.dist-info/METADATA
ecpay_invoice-1.0.7.dist-info/RECORD
ecpay_invoice-1.0.7.dist-info/WHEEL
ecpay_invoice-1.0.7.dist-info/top_level.txt
