Metadata-Version: 2.1
Name: ecpay-invoice
Version: 1.0.7
Summary: ecpay_invoice
Home-page: https://github.com/skypc785308/ecpay_invoice
Author: Hiskyz
Author-email: skypc785308@gmail.com
License: BSD License
Platform: UNKNOWN
Classifier: Development Status :: 5 - Production/Stable
Classifier: Operating System :: OS Independent
Classifier: Intended Audience :: Financial and Insurance Industry
Classifier: License :: OSI Approved :: BSD License
Classifier: Programming Language :: Python
Classifier: Programming Language :: Python :: 2.7
Classifier: Topic :: Software Development :: Libraries
Requires-Dist: requests
